dummy_autoupdate
