Metadata-Version: 1.2
Name: dummy-autoupdate
Version: 0.2.33
Summary: Dummy autoupdate for testing
Home-page: UNKNOWN
Author: Vladimir Starostin
Author-email: vladimir.starostin@uni-tuebingen.de
License: MIT
Platform: UNKNOWN
Requires-Python: >=3.7.2
